spaceweather/__init__.py
spaceweather/celestrak.py
spaceweather/core.py
spaceweather/gfz.py
spaceweather/omni.py
spaceweather/data/.cache
spaceweather/data/SW-All.txt
spaceweather/data/SW-Last5Years.txt
spaceweather/data/omni_extended/.cache
spaceweather-0.4.0.dist-info/licenses/COPYING.CCby4.0
spaceweather-0.4.0.dist-info/licenses/COPYING.GPLv2
spaceweather-0.4.0.dist-info/licenses/COPYING.data
spaceweather-0.4.0.dist-info/licenses/COPYING.gfz
spaceweather-0.4.0.dist-info/licenses/COPYING.omni
spaceweather-0.4.0.dist-info/METADATA
spaceweather-0.4.0.dist-info/WHEEL
spaceweather-0.4.0.dist-info/top_level.txt
spaceweather-0.4.0.dist-info/RECORD
