Metadata-Version: 2.4
Name: spaceweather
Version: 0.4.0
Summary: Python interface for space weather indices
Home-page: https://github.com/st-bender/pyspaceweather
Author: Stefan Bender
Author-email: sbender@iaa.es
License: GPLv2
Classifier: Development Status :: 4 - Beta
Classifier: Intended Audience :: Science/Research
Classifier: License :: OSI Approved :: GNU General Public License v2 (GPLv2)
Classifier: Programming Language :: Python
Classifier: Programming Language :: Python :: 2
Classifier: Programming Language :: Python :: 3
Classifier: Programming Language :: Python :: Implementation :: CPython
Classifier: Topic :: Scientific/Engineering :: Physics
Classifier: Topic :: Utilities
License-File: COPYING.CCby4.0
License-File: COPYING.GPLv2
License-File: COPYING.data
License-File: COPYING.gfz
License-File: COPYING.omni
Requires-Dist: numpy>=1.13.0
Requires-Dist: pandas
Requires-Dist: requests
Provides-Extra: tests
Requires-Dist: pytest; extra == "tests"
Requires-Dist: pytest-mock; extra == "tests"
Provides-Extra: all
Requires-Dist: pytest; extra == "all"
Requires-Dist: pytest-mock; extra == "all"
Dynamic: author
Dynamic: author-email
Dynamic: classifier
Dynamic: description
Dynamic: description-content-type
Dynamic: home-page
Dynamic: license
Dynamic: license-file
Dynamic: provides-extra
Dynamic: requires-dist
Dynamic: summary
